pyrostep/__init__.py
pyrostep/_install.py
pyrostep/shortcuts.py
pyrostep/steps.py
pyrostep/connection/__init__.py
pyrostep/connection/connection.py
pyrostep-2.11.22.dist-info/LICENSE
pyrostep-2.11.22.dist-info/METADATA
pyrostep-2.11.22.dist-info/WHEEL
pyrostep-2.11.22.dist-info/top_level.txt
pyrostep-2.11.22.dist-info/RECORD
