Metadata-Version: 2.1
Name: pyrostep
Version: 2.11.22
Summary: A Python library to handle steps in pyrogram framework.
Home-page: https://github.com/awolverp/pyrostep
Author: aWolver
License: MIT
Keywords: pyrostep,pyrogram,step handler,pyrogram helper,helper,pyrogram plugin,plugin,pyrogram connection
Classifier: Programming Language :: Python :: 3
Classifier: License :: OSI Approved :: MIT License
License-File: LICENSE
Requires-Dist: cachebox
